pymixin/__init__.py
pymixin/_mixin.cp39-win_amd64.pyd
pymixin/log.py
pymixin/main.py
pymixin/message_types.py
pymixin/mixin.dll
pymixin/mixin_api.py
pymixin/mixin_bot_api.py
pymixin/mixin_config.default.py
pymixin/mixin_config.py
pymixin/mixin_ws_api.py
pymixin/testnet.py
pymixin/utils.py
mixin_python-0.2.10.dist-info/LICENSE
mixin_python-0.2.10.dist-info/METADATA
mixin_python-0.2.10.dist-info/WHEEL
mixin_python-0.2.10.dist-info/top_level.txt
mixin_python-0.2.10.dist-info/RECORD
