Metadata-Version: 2.1
Name: mixin-python
Version: 0.2.10
Summary: Mixin Binding Project
Home-page: https://github.com/learnforpractice/mixin-python
Author: learnforpractice
License: GPL-3.0
Platform: UNKNOWN
License-File: LICENSE
Requires-Dist: PyJWT (>=2.4.0)
Requires-Dist: websockets (>=9.1)
Requires-Dist: cryptography (>=3.4.7)
Requires-Dist: dataclasses-json
Requires-Dist: httpx
